lolcatfigletgnuplotprint/LolcatFigletPrinter.py
lolcatfigletgnuplotprint/PlotPrinter.py
lolcatfigletgnuplotprint/__init__.py
lolcatfigletgnuplotprint/__main__.py
lolcatfigletgnuplotprint/_cli.py
lolcatfigletgnuplotprint/lolcatfigletgnuplotprint.egg-info/PKG-INFO
lolcatfigletgnuplotprint/lolcatfigletgnuplotprint.egg-info/SOURCES.txt
lolcatfigletgnuplotprint/lolcatfigletgnuplotprint.egg-info/dependency_links.txt
lolcatfigletgnuplotprint/lolcatfigletgnuplotprint.egg-info/requires.txt
lolcatfigletgnuplotprint/lolcatfigletgnuplotprint.egg-info/top_level.txt
lolcatfigletgnuplotprint/utils/CommandlinePrinter.py
lolcatfigletgnuplotprint/utils/Configuration.py
lolcatfigletgnuplotprint/utils/data_structures.py
lolcatfigletgnuplotprint/utils/dates.py
lolcatfigletgnuplotprint/utils/runtime.py
lolcatfigletgnuplotprint/utils/strings.py
lolcatfigletgnuplotprint/utils/transformations.py
lolcatfigletgnuplotprint/utils/types.py
lolcatfigletgnuplotprint-0.0.16.dist-info/entry_points.txt
lolcatfigletgnuplotprint-0.0.16.dist-info/WHEEL
lolcatfigletgnuplotprint-0.0.16.dist-info/METADATA
lolcatfigletgnuplotprint-0.0.16.dist-info/RECORD
